declination/WMM.COF
declination/__init__.py
declination/geomag.py
declination-1.0.2.dist-info/METADATA
declination-1.0.2.dist-info/WHEEL
declination-1.0.2.dist-info/top_level.txt
declination-1.0.2.dist-info/RECORD
